taoc/__init__.py
taoc-0.1.0.dist-info/METADATA
taoc-0.1.0.dist-info/WHEEL
taoc-0.1.0.dist-info/RECORD
