Metadata-Version: 2.1
Name: taoc
Version: 0.1.0
Summary: 
Author: taitep
Author-email: arvid@h.se
Requires-Python: >=3.12,<4.0
Classifier: Programming Language :: Python :: 3
Classifier: Programming Language :: Python :: 3.12
Requires-Dist: advent-of-code-data (>=2.0.1,<3.0.0)
